dbt_cloud_download_artifacts_action/dbt_cloud_helpers.py
dbt_cloud_download_artifacts_action/github_helpers.py
dbt_cloud_download_artifacts_action/logger.py
dbt_cloud_download_artifacts_action/main.py
dbt_cloud_download_artifacts_action/utils.py
dbt_cloud_download_artifacts_action/version.py
dbt_cloud_download_artifacts_action-0.2.1.dist-info/LICENSE
dbt_cloud_download_artifacts_action-0.2.1.dist-info/METADATA
dbt_cloud_download_artifacts_action-0.2.1.dist-info/WHEEL
dbt_cloud_download_artifacts_action-0.2.1.dist-info/entry_points.txt
dbt_cloud_download_artifacts_action-0.2.1.dist-info/top_level.txt
dbt_cloud_download_artifacts_action-0.2.1.dist-info/RECORD
